fast_file_encryption/__init__.py
fast_file_encryption/_about.py
fast_file_encryption/decryptor.py
fast_file_encryption/encryptor.py
fast_file_encryption/errors.py
fast_file_encryption/internals.py
fast_file_encryption/tools.py
fast_file_encryption-1.2.7.dist-info/licenses/LICENSE
fast_file_encryption-1.2.7.dist-info/METADATA
fast_file_encryption-1.2.7.dist-info/WHEEL
fast_file_encryption-1.2.7.dist-info/top_level.txt
fast_file_encryption-1.2.7.dist-info/RECORD
