Metadata-Version: 2.4
Name: fast-file-encryption
Version: 1.2.7
Summary: A simple and fast asynchronous file encryption library for large files and data streams.
Home-page: https://github.com/erbsland-dev/fast-file-encryption
Author: Erbsland DEV
Author-email: info@erbsland.dev
Project-URL: Documentation, https://erbsland-dev.github.io/fast-file-encryption/
Project-URL: Source, https://github.com/erbsland-dev/fast-file-encryption
Project-URL: Issues, https://github.com/erbsland-dev/fast-file-encryption/issues
Classifier: Development Status :: 5 - Production/Stable
Classifier: Intended Audience :: Developers
Classifier: Programming Language :: Python :: 3
Classifier: Programming Language :: Python :: 3 :: Only
Classifier: Programming Language :: Python :: 3.11
Classifier: Programming Language :: Python :: 3.12
Classifier: Programming Language :: Python :: 3.13
Classifier: License :: OSI Approved :: Apache Software License
Classifier: Operating System :: OS Independent
Classifier: Topic :: Security
Requires-Python: >=3.11
License-File: LICENSE
Requires-Dist: cryptography>=45.0.0
Dynamic: license-file
